streambatch/__init__.py
streambatch/module1.py
streambatch/savgol.py
streambatch-0.1.9.dist-info/METADATA
streambatch-0.1.9.dist-info/WHEEL
streambatch-0.1.9.dist-info/licenses/LICENSE
streambatch-0.1.9.dist-info/RECORD
