Metadata-Version: 2.1
Name: streambatch
Version: 0.1.9
Summary: Use this package to get daily, 10m resolution NDVI time series data for any location on Earth via the Streambatch.io API.
Project-URL: Homepage, https://github.com/tammer/streambatch
Author-email: Tammer Kamel <tammer@tammer.com>
License-File: LICENSE
Classifier: License :: OSI Approved :: MIT License
Classifier: Operating System :: OS Independent
Classifier: Programming Language :: Python :: 3
Requires-Python: >=3.7
Requires-Dist: pandas
Requires-Dist: pyarrow
Requires-Dist: requests
Requires-Dist: s3fs
Requires-Dist: scipy
